emlens/__init__.py
emlens/density_estimation.py
emlens/metrics.py
emlens/semaxis.py
emlens-0.0.11.dist-info/LICENSE
emlens-0.0.11.dist-info/METADATA
emlens-0.0.11.dist-info/WHEEL
emlens-0.0.11.dist-info/top_level.txt
emlens-0.0.11.dist-info/RECORD
