Metadata-Version: 2.1
Name: emlens
Version: 0.0.11
Summary: A lightweight toolbox for understanding embedding space
Home-page: https://github.com/skojaku/emlens
Author: Sadamori Kojaku
License: MIT
Keywords: word embedding,graph embedding
Platform: UNKNOWN
Classifier: Development Status :: 3 - Alpha
Classifier: Intended Audience :: Science/Research
Classifier: Topic :: Software Development
Classifier: License :: OSI Approved :: MIT License
Classifier: Programming Language :: Python :: 3.7
Classifier: Programming Language :: Python :: 3.8
License-File: LICENSE
Requires-Dist: faiss-cpu
Requires-Dist: tqdm
Requires-Dist: numba
Requires-Dist: numpy
Requires-Dist: scikit-learn
Requires-Dist: scipy
